{
  "info": {
    "_postman_id": "e456456e-93b4-4a91-a276-47596b75edd4",
    "name": "agendamento-hospital",
    "description": "# Collection relacionada ao Tech Challenge Fase 3 -> Sistema de Agendamento de Consultas",
    "schema": "https://schema.getpostman.com/json/collection/v2.1.0/collection.json",
    "_exporter_id": "27397573",
    "_collection_link": "https://go.postman.co/collection/27397573-e456456e-93b4-4a91-a276-47596b75edd4?source=collection_link"
  },
  "item": [
    {
      "name": "Usuarios",
      "item": [
        {
          "name": "Criar Paciente",
          "request": {
            "method": "POST",
            "header": [],
            "body": {
              "mode": "raw",
              "raw": "{\r\n  \"nome\": \"Maria Paciente\",\r\n  \"email\": \"paciente@email.com\",\r\n  \"password\": \"1234\",\r\n  \"role\": \"PACIENTE\"\r\n}",
              "options": {
                "raw": {
                  "language": "json"
                }
              }
            },
            "url": {
              "raw": "http://localhost:8080/usuarios",
              "protocol": "http",
              "host": [
                "localhost"
              ],
              "port": "8080",
              "path": [
                "usuarios"
              ]
            }
          },
          "response": []
        },
        {
          "name": "Criar Médico",
          "request": {
            "method": "POST",
            "header": [],
            "body": {
              "mode": "raw",
              "raw": "{\r\n  \"nome\": \"Dr. Carlos\",\r\n  \"email\": \"medico@email.com\",\r\n  \"password\": \"123456\",\r\n  \"role\": \"MEDICO\"\r\n}",
              "options": {
                "raw": {
                  "language": "json"
                }
              }
            },
            "url": {
              "raw": "http://localhost:8080/usuarios",
              "protocol": "http",
              "host": [
                "localhost"
              ],
              "port": "8080",
              "path": [
                "usuarios"
              ]
            }
          },
          "response": []
        },
        {
          "name": "Criar Enfermeiro",
          "event": [
            {
              "listen": "test",
              "script": {
                "exec": [
                  "pm.test(\"Returns 200 OK status\", () => {",
                  "    pm.response.to.have.status(200)",
                  "})"
                ],
                "type": "text/javascript",
                "packages": {},
                "requests": {}
              }
            }
          ],
          "request": {
            "method": "POST",
            "header": [],
            "body": {
              "mode": "raw",
              "raw": "{\n  \"nome\": \"Ana Enfermeira\",\n  \"email\": \"enfermeiro@email.com\",\n  \"password\": \"123456\",\n  \"role\": \"ENFERMEIRO\"\n}",
              "options": {
                "raw": {
                  "language": "json"
                }
              }
            },
            "url": {
              "raw": "http://localhost:8080/usuarios",
              "protocol": "http",
              "host": [
                "localhost"
              ],
              "port": "8080",
              "path": [
                "usuarios"
              ]
            },
            "description": "This request un-registers a token by using the token collection variable in the POST body.\n\nWe also added a test to ensure the response has a 200 OK status code."
          },
          "response": []
        },
        {
          "name": "Listar Usuários",
          "protocolProfileBehavior": {
            "disableBodyPruning": true
          },
          "request": {
            "auth": {
              "type": "basic",
              "basic": [
                {
                  "key": "password",
                  "value": "123456",
                  "type": "string"
                },
                {
                  "key": "username",
                  "value": "medico@email.com",
                  "type": "string"
                }
              ]
            },
            "method": "GET",
            "header": [],
            "body": {
              "mode": "raw",
              "raw": "",
              "options": {
                "raw": {
                  "language": "json"
                }
              }
            },
            "url": {
              "raw": "http://localhost:8080/usuarios",
              "protocol": "http",
              "host": [
                "localhost"
              ],
              "port": "8080",
              "path": [
                "usuarios"
              ]
            }
          },
          "response": []
        },
        {
          "name": "Deletar Usuário",
          "request": {
            "method": "DELETE",
            "header": [],
            "body": {
              "mode": "raw",
              "raw": ""
            },
            "url": {
              "raw": "http://localhost:8080/usuarios/1",
              "protocol": "http",
              "host": [
                "localhost"
              ],
              "port": "8080",
              "path": [
                "usuarios",
                "1"
              ]
            }
          },
          "response": []
        }
      ]
    },
    {
      "name": "Consultas",
      "item": [
        {
          "name": "Consulta",
          "event": [
            {
              "listen": "test",
              "script": {
                "exec": [
                  "pm.test(\"An access token is returned\", () => {",
                  "    pm.expect(pm.response.json()).to.have.property('token')",
                  "    pm.expect(pm.response.json().token).to.be.a('string')",
                  "    // Set the collection-scope \"token\" variable to the token received from the API",
                  "    // This lets us use it in other requests",
                  "    pm.collectionVariables.set('token', pm.response.json().token)",
                  "})",
                  ""
                ],
                "type": "text/javascript",
                "packages": {},
                "requests": {}
              }
            }
          ],
          "request": {
            "auth": {
              "type": "basic",
              "basic": [
                {
                  "key": "username",
                  "value": "enfermeiro@email.com",
                  "type": "string"
                },
                {
                  "key": "password",
                  "value": "123456",
                  "type": "string"
                }
              ]
            },
            "method": "POST",
            "header": [],
            "body": {
              "mode": "raw",
              "raw": "{\r\n  \"pacienteId\": 1,\r\n  \"medicoId\": 3,\r\n  \"dataConsulta\": \"2026-03-20T14:00\",\r\n  \"descricao\": \"Consulta de rotina\"\r\n}",
              "options": {
                "raw": {
                  "language": "json"
                }
              }
            },
            "url": {
              "raw": "http://localhost:8080/consultas",
              "protocol": "http",
              "host": [
                "localhost"
              ],
              "port": "8080",
              "path": [
                "consultas"
              ]
            },
            "description": "This returns a `token` that you can use to retrieve information later on.\n\nWe have included a test to confirm if a token is returned. We have also added test scripts to copy the token to the `token` collection variable. This makes it easy for us to reuse this token in other requests in the collection."
          },
          "response": []
        },
        {
          "name": "Consultas",
          "event": [
            {
              "listen": "test",
              "script": {
                "exec": [
                  "pm.test(\"A name is returned\", () => {",
                  "    pm.expect(pm.response.json()).to.have.property('name');",
                  "    pm.expect(pm.response.json().name).to.be.a('string');",
                  "})"
                ],
                "type": "text/javascript",
                "packages": {},
                "requests": {}
              }
            }
          ],
          "protocolProfileBehavior": {
            "disableBodyPruning": true
          },
          "request": {
            "auth": {
              "type": "basic",
              "basic": [
                {
                  "key": "username",
                  "value": "medico@email.com",
                  "type": "string"
                },
                {
                  "key": "password",
                  "value": "123456",
                  "type": "string"
                }
              ]
            },
            "method": "GET",
            "header": [],
            "body": {
              "mode": "raw",
              "raw": "",
              "options": {
                "raw": {
                  "language": "json"
                }
              }
            },
            "url": {
              "raw": "http://localhost:8080/consultas",
              "protocol": "http",
              "host": [
                "localhost"
              ],
              "port": "8080",
              "path": [
                "consultas"
              ]
            },
            "description": "This request uses the saved `token` collection variable to access a secret 'name' stored against that token.\n\nIn this request, we used the `token` collection variable as a query param to fetch the name generated for that token. We have added a test to check that a name is correctly returned."
          },
          "response": []
        },
        {
          "name": "Consultas Do Paciente",
          "event": [
            {
              "listen": "test",
              "script": {
                "exec": [
                  "pm.test(\"A name is returned\", () => {",
                  "    pm.expect(pm.response.json()).to.have.property('name');",
                  "    pm.expect(pm.response.json().name).to.be.a('string');",
                  "})"
                ],
                "type": "text/javascript",
                "packages": {},
                "requests": {}
              }
            }
          ],
          "protocolProfileBehavior": {
            "disableBodyPruning": true
          },
          "request": {
            "auth": {
              "type": "basic",
              "basic": [
                {
                  "key": "username",
                  "value": "paciente@email.com",
                  "type": "string"
                },
                {
                  "key": "password",
                  "value": "123456",
                  "type": "string"
                }
              ]
            },
            "method": "GET",
            "header": [],
            "body": {
              "mode": "raw",
              "raw": "",
              "options": {
                "raw": {
                  "language": "json"
                }
              }
            },
            "url": {
              "raw": "http://localhost:8080/consultas/minhas",
              "protocol": "http",
              "host": [
                "localhost"
              ],
              "port": "8080",
              "path": [
                "consultas",
                "minhas"
              ]
            },
            "description": "This request uses the saved `token` collection variable to access a secret 'name' stored against that token.\n\nIn this request, we used the `token` collection variable as a query param to fetch the name generated for that token. We have added a test to check that a name is correctly returned."
          },
          "response": []
        },
        {
          "name": "Atualizar Consulta",
          "event": [
            {
              "listen": "test",
              "script": {
                "exec": [
                  "pm.test(\"An access token is returned\", () => {",
                  "    pm.expect(pm.response.json()).to.have.property('token')",
                  "    pm.expect(pm.response.json().token).to.be.a('string')",
                  "    // Set the collection-scope \"token\" variable to the token received from the API",
                  "    // This lets us use it in other requests",
                  "    pm.collectionVariables.set('token', pm.response.json().token)",
                  "})",
                  ""
                ],
                "type": "text/javascript",
                "packages": {},
                "requests": {}
              }
            }
          ],
          "request": {
            "auth": {
              "type": "basic",
              "basic": [
                {
                  "key": "username",
                  "value": "medico@email.com",
                  "type": "string"
                },
                {
                  "key": "password",
                  "value": "123456",
                  "type": "string"
                }
              ]
            },
            "method": "PATCH",
            "header": [],
            "body": {
              "mode": "raw",
              "raw": "{\r\n  \"descricao\": \"Consulta cardiológica\",\r\n  \"status\": \"CANCELADA\"\r\n}",
              "options": {
                "raw": {
                  "language": "json"
                }
              }
            },
            "url": {
              "raw": "http://localhost:8080/consultas/1",
              "protocol": "http",
              "host": [
                "localhost"
              ],
              "port": "8080",
              "path": [
                "consultas",
                "1"
              ]
            },
            "description": "This returns a `token` that you can use to retrieve information later on.\n\nWe have included a test to confirm if a token is returned. We have also added test scripts to copy the token to the `token` collection variable. This makes it easy for us to reuse this token in other requests in the collection."
          },
          "response": []
        }
      ]
    }
  ],
  "event": [
    {
      "listen": "prerequest",
      "script": {
        "type": "text/javascript",
        "exec": [
          ""
        ]
      }
    },
    {
      "listen": "test",
      "script": {
        "type": "text/javascript",
        "exec": [
          ""
        ]
      }
    }
  ],
  "variable": [
    {
      "key": "token",
      "value": ""
    },
    {
      "key": "baseUrl",
      "value": "https://postman-integration-testing.glitch.me/"
    }
  ]
}